mindfoundry/__init__.py
mindfoundry/optaas/__init__.py
mindfoundry/optaas/client/__init__.py
mindfoundry/optaas/client/api_key.py
mindfoundry/optaas/client/client.py
mindfoundry/optaas/client/configuration.py
mindfoundry/optaas/client/constraint.py
mindfoundry/optaas/client/expressions.py
mindfoundry/optaas/client/goal.py
mindfoundry/optaas/client/objective.py
mindfoundry/optaas/client/parameter.py
mindfoundry/optaas/client/prediction.py
mindfoundry/optaas/client/result.py
mindfoundry/optaas/client/session.py
mindfoundry/optaas/client/task.py
mindfoundry/optaas/client/user_defined_configuration.py
mindfoundry/optaas/client/utils.py
mindfoundry/optaas/client/version_check.py
mindfoundry/optaas/client/viz.py
mindfoundry/optaas/client/sklearn_pipelines/__init__.py
mindfoundry/optaas/client/sklearn_pipelines/mixin.py
mindfoundry/optaas/client/sklearn_pipelines/parameter_maker.py
mindfoundry/optaas/client/sklearn_pipelines/sklearn_task.py
mindfoundry/optaas/client/sklearn_pipelines/utils.py
mindfoundry/optaas/client/sklearn_pipelines/estimators/__init__.py
mindfoundry/optaas/client/sklearn_pipelines/estimators/ada_boost.py
mindfoundry/optaas/client/sklearn_pipelines/estimators/ensemble.py
mindfoundry/optaas/client/sklearn_pipelines/estimators/ica.py
mindfoundry/optaas/client/sklearn_pipelines/estimators/k_neighbors.py
mindfoundry/optaas/client/sklearn_pipelines/estimators/linear_model.py
mindfoundry/optaas/client/sklearn_pipelines/estimators/pca.py
mindfoundry/optaas/client/sklearn_pipelines/estimators/svc.py
mindfoundry/optaas/client/sklearn_pipelines/estimators/voting.py
mindfoundry/optaas/client/sklearn_pipelines/estimators/xgboost.py
mindfoundry_optaas_client-1.4.4.dist-info/LICENSE
mindfoundry_optaas_client-1.4.4.dist-info/METADATA
mindfoundry_optaas_client-1.4.4.dist-info/WHEEL
mindfoundry_optaas_client-1.4.4.dist-info/top_level.txt
mindfoundry_optaas_client-1.4.4.dist-info/RECORD
