Metadata-Version: 2.1
Name: mindfoundry-optaas-client
Version: 1.4.4
Summary: Mind Foundry Optimization as a Service: Python Client
Home-page: https://mindfoundry.ai/optaas
Author: Mind Foundry Ltd
Author-email: optaas@mindfoundry.ai
License: MIT License
Keywords: bayesian optimization,bayesian,optimization,machine learning,machine-learning,hyperparameter,hyper-parameters,model selection,model-selection
Platform: Any
Classifier: Development Status :: 4 - Beta
Classifier: Intended Audience :: Developers
Classifier: Intended Audience :: Financial and Insurance Industry
Classifier: Intended Audience :: Science/Research
Classifier: Topic :: Scientific/Engineering :: Artificial Intelligence
Classifier: License :: OSI Approved :: MIT License
Classifier: Programming Language :: Python :: 3.9
Classifier: Operating System :: OS Independent
License-File: LICENSE
Requires-Dist: requests
Requires-Dist: holoviews (<1.13)
Requires-Dist: sympy
Requires-Dist: loguru
Provides-Extra: sklearn
Requires-Dist: scikit-learn ; extra == 'sklearn'
